{
	"adult": false,
	"also_known_as": [],
	"biography": "From Wikipedia, the free encyclopedia.\n\nFernando Meirelles (born November 9, 1955 in São Paulo, Brazil) is a Brazilian film director.\n\nHe was nominated for an Academy Award for Best Director in 2004 for his work in the Brazilian film City of God, released in 2002 in Brazil and in 2003 in the U.S. by Miramax Films. He was also nominated for the Golden Globe Best Director award in 2005 for The Constant Gardener.\n\nDescription above from the Wikipedia article Fernando Meirelles, licensed under CC-BY-SA, full list of contributors on Wikipedia.",
	"birthday": "1955-11-09",
	"deathday": "",
	"homepage": "",
	"id": 8557,
	"imdb_id": "nm0576987",
	"name": "Fernando Meirelles",
	"place_of_birth": "São Paulo, Brazil",
	"popularity": 1.4749,
	"profile_path": "/j77Z3f2m0e211ocFhPJu5ZiO12R.jpg"
}